[
    {
        "Symbol": "OKTA",
        "Company": "Okta, Inc.",
        "Earnings Date": "March 2, 2026 at 4 PM EST",
        "EPS Estimate": 0.85,
        "Reported EPS": "-",
        "Surprise (%)": "-"
    },
    {
        "Symbol": "OKTA",
        "Company": "Okta, Inc.",
        "Earnings Date": "December 2, 2025 at 4 PM EST",
        "EPS Estimate": 0.76,
        "Reported EPS": "0.82",
        "Surprise (%)": "+8.05"
    },
    {
        "Symbol": "OKTA",
        "Company": "Okta, Inc.",
        "Earnings Date": "August 26, 2025 at 4 PM EDT",
        "EPS Estimate": 0.85,
        "Reported EPS": "0.91",
        "Surprise (%)": "+7.57"
    },
    {
        "Symbol": "OKTA",
        "Company": "Okta, Inc.",
        "Earnings Date": "May 27, 2025 at 4 PM EDT",
        "EPS Estimate": 0.77,
        "Reported EPS": "0.86",
        "Surprise (%)": "+11.49"
    },
    {
        "Symbol": "OKTA",
        "Company": "Okta, Inc.",
        "Earnings Date": "March 3, 2025 at 4 PM EST",
        "EPS Estimate": 0.74,
        "Reported EPS": "0.78",
        "Surprise (%)": "+5.95"
    },
    {
        "Symbol": "OKTA",
        "Company": "Okta, Inc.",
        "Earnings Date": "December 3, 2024 at 4 PM EST",
        "EPS Estimate": 0.58,
        "Reported EPS": "0.67",
        "Surprise (%)": "+14.83"
    },
    {
        "Symbol": "OKTA",
        "Company": "Okta, Inc.",
        "Earnings Date": "August 28, 2024 at 4 PM EDT",
        "EPS Estimate": 0.61,
        "Reported EPS": "0.72",
        "Surprise (%)": "+17.62"
    },
    {
        "Symbol": "OKTA",
        "Company": "Okta, Inc.",
        "Earnings Date": "May 29, 2024 at 4 PM EDT",
        "EPS Estimate": 0.55,
        "Reported EPS": "0.65",
        "Surprise (%)": "+19.13"
    },
    {
        "Symbol": "OKTA",
        "Company": "Okta, Inc.",
        "Earnings Date": "February 28, 2024 at 4 PM EST",
        "EPS Estimate": 0.51,
        "Reported EPS": "0.63",
        "Surprise (%)": "+24.03"
    },
    {
        "Symbol": "OKTA",
        "Company": "Okta, Inc.",
        "Earnings Date": "November 29, 2023 at 7 AM EST",
        "EPS Estimate": 0.29,
        "Reported EPS": "0.44",
        "Surprise (%)": "+50.79"
    },
    {
        "Symbol": "OKTA",
        "Company": "Okta, Inc.",
        "Earnings Date": "August 30, 2023 at 4 PM EDT",
        "EPS Estimate": 0.21,
        "Reported EPS": "0.31",
        "Surprise (%)": "+44.48"
    },
    {
        "Symbol": "OKTA",
        "Company": "Okta, Inc.",
        "Earnings Date": "May 31, 2023 at 4 PM EDT",
        "EPS Estimate": 0.12,
        "Reported EPS": "0.22",
        "Surprise (%)": "+85.54"
    },
    {
        "Symbol": "OKTA",
        "Company": "Okta, Inc.",
        "Earnings Date": "March 1, 2023 at 4 PM EST",
        "EPS Estimate": 0.09,
        "Reported EPS": "0.3",
        "Surprise (%)": "+233.07"
    },
    {
        "Symbol": "OKTA",
        "Company": "Okta, Inc.",
        "Earnings Date": "November 30, 2022 at 4 PM EST",
        "EPS Estimate": -0.24,
        "Reported EPS": "-",
        "Surprise (%)": "+98.45"
    },
    {
        "Symbol": "OKTA",
        "Company": "Okta, Inc.",
        "Earnings Date": "August 31, 2022 at 4 PM EDT",
        "EPS Estimate": -0.3,
        "Reported EPS": "-0.1",
        "Surprise (%)": "+67.1"
    },
    {
        "Symbol": "OKTA",
        "Company": "Okta, Inc.",
        "Earnings Date": "June 2, 2022 at 4 PM EDT",
        "EPS Estimate": -0.34,
        "Reported EPS": "-0.27",
        "Surprise (%)": "+20.67"
    },
    {
        "Symbol": "OKTA",
        "Company": "Okta, Inc.",
        "Earnings Date": "March 2, 2022 at 4 PM EST",
        "EPS Estimate": -0.24,
        "Reported EPS": "-0.18",
        "Surprise (%)": "+24.88"
    },
    {
        "Symbol": "OKTA",
        "Company": "Okta, Inc.",
        "Earnings Date": "December 1, 2021 at 4 PM EST",
        "EPS Estimate": -0.23,
        "Reported EPS": "-0.07",
        "Surprise (%)": "+69.98"
    },
    {
        "Symbol": "OKTA",
        "Company": "Okta, Inc.",
        "Earnings Date": "September 1, 2021 at 4 PM EDT",
        "EPS Estimate": -0.33,
        "Reported EPS": "-0.11",
        "Surprise (%)": "+66.91"
    },
    {
        "Symbol": "OKTA",
        "Company": "Okta, Inc.",
        "Earnings Date": "May 26, 2021 at 4 PM EDT",
        "EPS Estimate": -0.2,
        "Reported EPS": "-0.1",
        "Surprise (%)": "+50"
    },
    {
        "Symbol": "OKTA",
        "Company": "Okta, Inc.",
        "Earnings Date": "March 3, 2021 at 4 PM EST",
        "EPS Estimate": -0.01,
        "Reported EPS": "0.06",
        "Surprise (%)": "+646.95"
    },
    {
        "Symbol": "OKTA",
        "Company": "Okta, Inc.",
        "Earnings Date": "December 2, 2020 at 4 PM EST",
        "EPS Estimate": -0.01,
        "Reported EPS": "0.04",
        "Surprise (%)": "+488.73"
    },
    {
        "Symbol": "OKTA",
        "Company": "Okta, Inc.",
        "Earnings Date": "August 27, 2020 at 4 PM EDT",
        "EPS Estimate": -0.02,
        "Reported EPS": "0.07",
        "Surprise (%)": "+479.4"
    },
    {
        "Symbol": "OKTA",
        "Company": "Okta, Inc.",
        "Earnings Date": "May 28, 2020 at 4 PM EDT",
        "EPS Estimate": -0.17,
        "Reported EPS": "-0.07",
        "Surprise (%)": "+58.35"
    },
    {
        "Symbol": "OKTA",
        "Company": "Okta, Inc.",
        "Earnings Date": "March 5, 2020 at 4 PM EST",
        "EPS Estimate": -0.05,
        "Reported EPS": "-0.01",
        "Surprise (%)": "+78.11"
    },
    {
        "Symbol": "OKTA",
        "Company": "Okta, Inc.",
        "Earnings Date": "December 5, 2019 at 4 PM EST",
        "EPS Estimate": -0.12,
        "Reported EPS": "-0.07",
        "Surprise (%)": "+42.69"
    },
    {
        "Symbol": "OKTA",
        "Company": "Okta, Inc.",
        "Earnings Date": "August 28, 2019 at 4 PM EDT",
        "EPS Estimate": -0.1,
        "Reported EPS": "-0.05",
        "Surprise (%)": "+51.4"
    },
    {
        "Symbol": "OKTA",
        "Company": "Okta, Inc.",
        "Earnings Date": "May 30, 2019 at 4 PM EDT",
        "EPS Estimate": -0.21,
        "Reported EPS": "-0.19",
        "Surprise (%)": "+9.78"
    },
    {
        "Symbol": "OKTA",
        "Company": "Okta, Inc.",
        "Earnings Date": "March 7, 2019 at 4 PM EST",
        "EPS Estimate": -0.08,
        "Reported EPS": "-0.04",
        "Surprise (%)": "+52.17"
    },
    {
        "Symbol": "OKTA",
        "Company": "Okta, Inc.",
        "Earnings Date": "December 5, 2018 at 4 PM EST",
        "EPS Estimate": -0.11,
        "Reported EPS": "-0.04",
        "Surprise (%)": "+64.76"
    },
    {
        "Symbol": "OKTA",
        "Company": "Okta, Inc.",
        "Earnings Date": "September 6, 2018 at 4 PM EDT",
        "EPS Estimate": -0.19,
        "Reported EPS": "-0.15",
        "Surprise (%)": "+21.34"
    },
    {
        "Symbol": "OKTA",
        "Company": "Okta, Inc.",
        "Earnings Date": "June 6, 2018 at 4 PM EDT",
        "EPS Estimate": -0.16,
        "Reported EPS": "-0.09",
        "Surprise (%)": "+42.98"
    },
    {
        "Symbol": "OKTA",
        "Company": "Okta, Inc.",
        "Earnings Date": "March 7, 2018 at 4 PM EST",
        "EPS Estimate": -0.15,
        "Reported EPS": "-0.1",
        "Surprise (%)": "+32.22"
    },
    {
        "Symbol": "OKTA",
        "Company": "Okta, Inc.",
        "Earnings Date": "December 6, 2017 at 4 PM EST",
        "EPS Estimate": -0.24,
        "Reported EPS": "-0.19",
        "Surprise (%)": "+21.38"
    },
    {
        "Symbol": "OKTA",
        "Company": "Okta, Inc.",
        "Earnings Date": "September 7, 2017 at 4 PM EDT",
        "EPS Estimate": -0.26,
        "Reported EPS": "-0.16",
        "Surprise (%)": "+37.5"
    },
    {
        "Symbol": "OKTA",
        "Company": "Okta, Inc.",
        "Earnings Date": "June 7, 2017 at 4 PM EDT",
        "EPS Estimate": -0.61,
        "Reported EPS": "-0.5",
        "Surprise (%)": "+18.35"
    }
]