[
    {
        "Symbol": "LLYVK",
        "Company": "Liberty Live Holdings, Inc.",
        "Earnings Date": "February 26, 2026 at 8 AM EST",
        "EPS Estimate": -1.27,
        "Reported EPS": "-",
        "Surprise (%)": "-"
    },
    {
        "Symbol": "LLYVK",
        "Company": "Liberty Live Holdings, Inc.",
        "Earnings Date": "November 5, 2025 at 7 PM EST",
        "EPS Estimate": 1.17,
        "Reported EPS": "-0.85",
        "Surprise (%)": "-172.36"
    },
    {
        "Symbol": "LLYVK",
        "Company": "Liberty Live Holdings, Inc.",
        "Earnings Date": "May 6, 2025 at 8 PM EDT",
        "EPS Estimate": 0.04,
        "Reported EPS": "-",
        "Surprise (%)": "-100"
    },
    {
        "Symbol": "LLYVK",
        "Company": "Liberty Live Holdings, Inc.",
        "Earnings Date": "February 26, 2025 at 7 PM EST",
        "EPS Estimate": -0.42,
        "Reported EPS": "0.88",
        "Surprise (%)": "+309.07"
    },
    {
        "Symbol": "LLYVK",
        "Company": "Liberty Live Holdings, Inc.",
        "Earnings Date": "November 3, 2023 at 2 PM EDT",
        "EPS Estimate": 0.98,
        "Reported EPS": "0.58",
        "Surprise (%)": "-41.22"
    }
]