{
    "recommendationTrend": {
        "trend": [
            {
                "period": "0m",
                "strongBuy": 3,
                "buy": 9,
                "hold": 3,
                "sell": 0,
                "strongSell": 2
            },
            {
                "period": "-1m",
                "strongBuy": 3,
                "buy": 9,
                "hold": 3,
                "sell": 0,
                "strongSell": 2
            },
            {
                "period": "-2m",
                "strongBuy": 3,
                "buy": 9,
                "hold": 3,
                "sell": 0,
                "strongSell": 2
            },
            {
                "period": "-3m",
                "strongBuy": 3,
                "buy": 8,
                "hold": 3,
                "sell": 0,
                "strongSell": 2
            }
        ],
        "maxAge": 86400
    },
    "equityPerformance": {
        "maxAge": 1,
        "benchmark": {
            "symbol": "^GSPC",
            "shortName": "S&P 500"
        },
        "performanceOverview": {
            "asOfDate": {
                "raw": 1766966400,
                "fmt": "2025-12-29"
            },
            "fiveDaysReturn": {
                "raw": 0.024824921,
                "fmt": "2.48%"
            },
            "oneMonthReturn": {
                "raw": 0.10645275,
                "fmt": "10.65%"
            },
            "threeMonthReturn": {
                "raw": 0.13134754,
                "fmt": "13.13%"
            },
            "sixMonthReturn": {
                "raw": 0.26042792,
                "fmt": "26.04%"
            },
            "ytdReturnPct": {
                "raw": 0.38360408,
                "fmt": "38.36%"
            },
            "oneYearTotalReturn": {
                "raw": 0.377569,
                "fmt": "37.76%"
            },
            "twoYearTotalReturn": {
                "raw": 0.80117345,
                "fmt": "80.12%"
            },
            "threeYearTotalReturn": {
                "raw": 0.86154336,
                "fmt": "86.15%"
            },
            "fiveYearTotalReturn": {
                "raw": 1.1476407,
                "fmt": "114.76%"
            },
            "tenYearTotalReturn": {
                "raw": 1.588854,
                "fmt": "158.89%"
            },
            "maxReturn": {
                "raw": 694.10645,
                "fmt": "69,410.64%"
            }
        },
        "performanceOverviewBenchmark": {
            "asOfDate": {
                "raw": 1766966400,
                "fmt": "2025-12-29"
            },
            "fiveDaysReturn": {
                "raw": 0.01042362,
                "fmt": "1.04%"
            },
            "oneMonthReturn": {
                "raw": 0.008271229,
                "fmt": "0.83%"
            },
            "threeMonthReturn": {
                "raw": 0.036709588,
                "fmt": "3.67%"
            },
            "sixMonthReturn": {
                "raw": 0.11868818,
                "fmt": "11.87%"
            },
            "ytdReturnPct": {
                "raw": 0.17412016,
                "fmt": "17.41%"
            },
            "oneYearTotalReturn": {
                "raw": 0.1565777,
                "fmt": "15.66%"
            },
            "twoYearTotalReturn": {
                "raw": 0.44779587,
                "fmt": "44.78%"
            },
            "threeYearTotalReturn": {
                "raw": 0.79403424,
                "fmt": "79.40%"
            },
            "fiveYearTotalReturn": {
                "raw": 0.85287523,
                "fmt": "85.29%"
            },
            "tenYearTotalReturn": {
                "raw": 2.322687,
                "fmt": "232.27%"
            },
            "maxReturn": {
                "raw": 390.0385,
                "fmt": "39,003.85%"
            }
        }
    },
    "quoteUnadjustedPerformanceOverview": {
        "maxAge": 1,
        "benchmark": {
            "symbol": "^GSPC",
            "shortName": "S&P 500"
        },
        "performanceOverview": {
            "asOfDate": {
                "raw": 1766966400,
                "fmt": "2025-12-29"
            },
            "fiveDaysReturn": {
                "raw": 0.024824921,
                "fmt": "2.48%"
            },
            "oneMonthReturn": {
                "raw": 0.10645275,
                "fmt": "10.65%"
            },
            "threeMonthReturn": {
                "raw": 0.12315567,
                "fmt": "12.32%"
            },
            "sixMonthReturn": {
                "raw": 0.24235852,
                "fmt": "24.24%"
            },
            "ytdReturnPct": {
                "raw": 0.34172186,
                "fmt": "34.17%"
            },
            "oneYearTotalReturn": {
                "raw": 0.33586934,
                "fmt": "33.59%"
            },
            "twoYearTotalReturn": {
                "raw": 0.70010334,
                "fmt": "70.01%"
            },
            "threeYearTotalReturn": {
                "raw": 0.68100595,
                "fmt": "68.10%"
            },
            "fiveYearTotalReturn": {
                "raw": 0.83055323,
                "fmt": "83.06%"
            },
            "tenYearTotalReturn": {
                "raw": 0.9466371,
                "fmt": "94.66%"
            },
            "maxReturn": {
                "raw": 694.10645,
                "fmt": "69,410.64%"
            }
        },
        "performanceOverviewBenchmark": {
            "asOfDate": {
                "raw": 1766966400,
                "fmt": "2025-12-29"
            },
            "fiveDaysReturn": {
                "raw": 0.01042362,
                "fmt": "1.04%"
            },
            "oneMonthReturn": {
                "raw": 0.008271229,
                "fmt": "0.83%"
            },
            "threeMonthReturn": {
                "raw": 0.036709588,
                "fmt": "3.67%"
            },
            "sixMonthReturn": {
                "raw": 0.11868818,
                "fmt": "11.87%"
            },
            "ytdReturnPct": {
                "raw": 0.17412016,
                "fmt": "17.41%"
            },
            "oneYearTotalReturn": {
                "raw": 0.1565777,
                "fmt": "15.66%"
            },
            "twoYearTotalReturn": {
                "raw": 0.44779587,
                "fmt": "44.78%"
            },
            "threeYearTotalReturn": {
                "raw": 0.79403424,
                "fmt": "79.40%"
            },
            "fiveYearTotalReturn": {
                "raw": 0.85287523,
                "fmt": "85.29%"
            },
            "tenYearTotalReturn": {
                "raw": 2.322687,
                "fmt": "232.27%"
            },
            "maxReturn": {
                "raw": 390.0385,
                "fmt": "39,003.85%"
            }
        }
    },
    "defaultKeyStatistics": {
        "maxAge": 1,
        "priceHint": {
            "raw": 2,
            "fmt": "2",
            "longFmt": "2"
        },
        "enterpriseValue": {
            "raw": -44853551104,
            "fmt": "-44.85B",
            "longFmt": "-44,853,551,104"
        },
        "forwardPE": {
            "raw": 11.569057,
            "fmt": "11.57"
        },
        "profitMargins": {
            "raw": 0.21877001,
            "fmt": "21.88%"
        },
        "floatShares": {
            "raw": 264042425,
            "fmt": "264.04M",
            "longFmt": "264,042,425"
        },
        "sharesOutstanding": {
            "raw": 279312436,
            "fmt": "279.31M",
            "longFmt": "279,312,436"
        },
        "sharesShort": {
            "raw": 4306448,
            "fmt": "4.31M",
            "longFmt": "4,306,448"
        },
        "sharesShortPriorMonth": {
            "raw": 4752235,
            "fmt": "4.75M",
            "longFmt": "4,752,235"
        },
        "sharesShortPreviousMonthDate": {
            "raw": 1763078400,
            "fmt": "2025-11-14"
        },
        "dateShortInterest": {
            "raw": 1765756800,
            "fmt": "2025-12-15"
        },
        "sharesPercentSharesOut": {
            "raw": 0.0154,
            "fmt": "1.54%"
        },
        "heldPercentInsiders": {
            "raw": 0.00434,
            "fmt": "0.43%"
        },
        "heldPercentInstitutions": {
            "raw": 0.96325,
            "fmt": "96.32%"
        },
        "shortRatio": {
            "raw": 2.44,
            "fmt": "2.44"
        },
        "shortPercentOfFloat": {
            "raw": 0.0178,
            "fmt": "1.78%"
        },
        "beta": {
            "raw": 1.453,
            "fmt": "1.45"
        },
        "impliedSharesOutstanding": {
            "raw": 283695343,
            "fmt": "283.7M",
            "longFmt": "283,695,343"
        },
        "morningStarOverallRating": {},
        "morningStarRiskRating": {},
        "category": null,
        "bookValue": {
            "raw": 85.335,
            "fmt": "85.33"
        },
        "priceToBook": {
            "raw": 1.543212,
            "fmt": "1.54"
        },
        "annualReportExpenseRatio": {},
        "ytdReturn": {},
        "qtdReturn": {},
        "beta3Year": {},
        "totalAssets": {},
        "yield": {},
        "fundFamily": null,
        "fundInceptionDate": {},
        "legalType": null,
        "threeYearAverageReturn": {},
        "fiveYearAverageReturn": {},
        "priceToSalesTrailing12Months": {},
        "lastFiscalYearEnd": {
            "raw": 1735603200,
            "fmt": "2024-12-31"
        },
        "nextFiscalYearEnd": {
            "raw": 1767139200,
            "fmt": "2025-12-31"
        },
        "mostRecentQuarter": {
            "raw": 1759190400,
            "fmt": "2025-09-30"
        },
        "earningsQuarterlyGrowth": {
            "raw": 0.179,
            "fmt": "17.90%"
        },
        "revenueQuarterlyGrowth": {},
        "netIncomeToCommon": {
            "raw": 2756999936,
            "fmt": "2.76B",
            "longFmt": "2,756,999,936"
        },
        "trailingEps": {
            "raw": 9.38,
            "fmt": "9.38"
        },
        "forwardEps": {
            "raw": 11.38295,
            "fmt": "11.38"
        },
        "pegRatio": {},
        "lastSplitFactor": "2:1",
        "lastSplitDate": {
            "raw": 991267200,
            "fmt": "2001-05-31"
        },
        "enterpriseToRevenue": {
            "raw": -3.292,
            "fmt": "-3.29"
        },
        "enterpriseToEbitda": {},
        "52WeekChange": {
            "raw": 0.34773302,
            "fmt": "34.77%"
        },
        "SandP52WeekChange": {
            "raw": 0.17823458,
            "fmt": "17.82%"
        },
        "lastDividendValue": {
            "raw": 0.84,
            "fmt": "0.84"
        },
        "lastDividendDate": {
            "raw": 1759276800,
            "fmt": "2025-10-01"
        },
        "lastCapGain": {},
        "annualHoldingsTurnover": {},
        "latestFundingDate": {},
        "latestAmountRaised": {},
        "latestImpliedValuation": {},
        "latestShareClass": null,
        "leadInvestor": null,
        "fundingToDate": {},
        "totalFundingRounds": {}
    },
    "summaryProfile": {
        "address1": "One Congress Street",
        "city": "Boston",
        "state": "MA",
        "zip": "02114-2016",
        "country": "United States",
        "phone": "617 786 3000",
        "website": "https://www.statestreet.com",
        "industry": "Asset Management",
        "industryKey": "asset-management",
        "industryDisp": "Asset Management",
        "sector": "Financial Services",
        "sectorKey": "financial-services",
        "sectorDisp": "Financial Services",
        "longBusinessSummary": "State Street Corporation provides various financial products and services to institutional investors. The company offers custody, accounting, and fund administration services for traditional and alternative assets, as well as multi-asset class investments; recordkeeping, client reporting, and investment book of record, transaction management, loans, cash, derivatives, and collateral services; investor services operations outsourcing; performance, risk, and compliance analytics; financial data management to support institutional investors; foreign exchange, brokerage, and other trading services; securities finance, such as prime services products; and deposit and short-term investment facilities. It also provides the State Street Alpha platform that combines portfolio management, trading and execution, analytics and compliance tools, and advanced data aggregation and integration with other industry platforms and providers; front-office technology that automates and simplifies the institutional investment process comprising portfolio management and risk analytics, trading, and post-trade settlement with integrated compliance and managed data; investment management solutions; and portfolio management, trading compliance, and manager/sponsor communication. In addition, the company offers investment management solutions, such as strategies across equity, fixed income, cash, multi-asset, and alternatives; SPDR ETFs and index funds; and defined benefit, defined contribution, and outsourced chief investment officer services. The company provides its products and services to mutual funds, collective investment funds and other investment pools, corporate and public retirement plans, insurance companies, investment managers, foundations, and endowments. It has a strategic alliance with UC Investments to expand access to wealth-building tools for individuals. The company was founded in 1792 and is headquartered in Boston, Massachusetts.",
        "fullTimeEmployees": 51564,
        "companyOfficers": [],
        "irWebsite": "http://phx.corporate-ir.net/phoenix.zhtml?c=78261&p=irol-IRHome",
        "executiveTeam": [],
        "maxAge": 86400
    },
    "financialsTemplate": {
        "code": "B",
        "maxAge": 1
    },
    "summaryDetail": {
        "maxAge": 1,
        "priceHint": {
            "raw": 2,
            "fmt": "2",
            "longFmt": "2"
        },
        "previousClose": {
            "raw": 132.28,
            "fmt": "132.28"
        },
        "open": {
            "raw": 132.23,
            "fmt": "132.23"
        },
        "dayLow": {
            "raw": 130.62,
            "fmt": "130.62"
        },
        "dayHigh": {
            "raw": 132.95,
            "fmt": "132.95"
        },
        "regularMarketPreviousClose": {
            "raw": 132.28,
            "fmt": "132.28"
        },
        "regularMarketOpen": {
            "raw": 132.23,
            "fmt": "132.23"
        },
        "regularMarketDayLow": {
            "raw": 130.62,
            "fmt": "130.62"
        },
        "regularMarketDayHigh": {
            "raw": 132.95,
            "fmt": "132.95"
        },
        "dividendRate": {
            "raw": 3.36,
            "fmt": "3.36"
        },
        "dividendYield": {
            "raw": 0.0254,
            "fmt": "2.54%"
        },
        "exDividendDate": {
            "raw": 1767312000,
            "fmt": "2026-01-02"
        },
        "payoutRatio": {
            "raw": 0.3312,
            "fmt": "33.12%"
        },
        "fiveYearAvgDividendYield": {
            "raw": 3.04,
            "fmt": "3.04"
        },
        "beta": {
            "raw": 1.453,
            "fmt": "1.45"
        },
        "trailingPE": {
            "raw": 14.039446,
            "fmt": "14.04"
        },
        "forwardPE": {
            "raw": 11.569057,
            "fmt": "11.57"
        },
        "volume": {
            "raw": 922960,
            "fmt": "922.96k",
            "longFmt": "922,960"
        },
        "regularMarketVolume": {
            "raw": 922960,
            "fmt": "922.96k",
            "longFmt": "922,960"
        },
        "averageVolume": {
            "raw": 2006393,
            "fmt": "2.01M",
            "longFmt": "2,006,393"
        },
        "averageVolume10days": {
            "raw": 2327180,
            "fmt": "2.33M",
            "longFmt": "2,327,180"
        },
        "averageDailyVolume10Day": {
            "raw": 2327180,
            "fmt": "2.33M",
            "longFmt": "2,327,180"
        },
        "bid": {
            "raw": 131.28,
            "fmt": "131.28"
        },
        "ask": {
            "raw": 136.06,
            "fmt": "136.06"
        },
        "bidSize": {
            "raw": 40000,
            "fmt": "40k",
            "longFmt": "40,000"
        },
        "askSize": {
            "raw": 30000,
            "fmt": "30k",
            "longFmt": "30,000"
        },
        "marketCap": {
            "raw": 37359837184,
            "fmt": "37.36B",
            "longFmt": "37,359,837,184"
        },
        "yield": {},
        "ytdReturn": {},
        "qtdReturn": {},
        "totalAssets": {},
        "expireDate": {},
        "strikePrice": {},
        "openInterest": {},
        "fiftyTwoWeekLow": {
            "raw": 72.81,
            "fmt": "72.81"
        },
        "fiftyTwoWeekHigh": {
            "raw": 133.0,
            "fmt": "133.00"
        },
        "allTimeHigh": {
            "raw": 133.0,
            "fmt": "133.00"
        },
        "allTimeLow": {
            "raw": 0.169922,
            "fmt": "0.17"
        },
        "priceToSalesTrailing12Months": {
            "raw": 2.741805,
            "fmt": "2.74"
        },
        "fiftyDayAverage": {
            "raw": 120.0568,
            "fmt": "120.06"
        },
        "twoHundredDayAverage": {
            "raw": 106.5826,
            "fmt": "106.58"
        },
        "trailingAnnualDividendRate": {
            "raw": 3.12,
            "fmt": "3.12"
        },
        "trailingAnnualDividendYield": {
            "raw": 0.023586331,
            "fmt": "2.36%"
        },
        "navPrice": {},
        "currency": "USD",
        "fromCurrency": null,
        "toCurrency": null,
        "lastMarket": null,
        "coinMarketCapLink": null,
        "volume24Hr": {},
        "volumeAllCurrencies": {},
        "circulatingSupply": {},
        "algorithm": null,
        "maxSupply": {},
        "totalSupply": {},
        "startDate": {},
        "tradeable": false,
        "fullyDilutedValue": {},
        "volume24HrMarketCapPercent": {}
    },
    "earnings": {
        "maxAge": 86400,
        "earningsChart": {
            "quarterly": [
                {
                    "date": "4Q2024",
                    "actual": {
                        "raw": 2.6,
                        "fmt": "2.60"
                    },
                    "estimate": {
                        "raw": 2.44106,
                        "fmt": "2.44"
                    },
                    "fiscalQuarter": "4Q2024",
                    "calendarQuarter": "4Q2024",
                    "difference": "0.16",
                    "surprisePct": "6.51"
                },
                {
                    "date": "1Q2025",
                    "actual": {
                        "raw": 2.04,
                        "fmt": "2.04"
                    },
                    "estimate": {
                        "raw": 2.0059,
                        "fmt": "2.01"
                    },
                    "fiscalQuarter": "1Q2025",
                    "calendarQuarter": "1Q2025",
                    "difference": "0.03",
                    "surprisePct": "1.7"
                },
                {
                    "date": "2Q2025",
                    "actual": {
                        "raw": 2.53,
                        "fmt": "2.53"
                    },
                    "estimate": {
                        "raw": 2.36309,
                        "fmt": "2.36"
                    },
                    "fiscalQuarter": "2Q2025",
                    "calendarQuarter": "2Q2025",
                    "difference": "0.17",
                    "surprisePct": "7.06"
                },
                {
                    "date": "3Q2025",
                    "actual": {
                        "raw": 2.78,
                        "fmt": "2.78"
                    },
                    "estimate": {
                        "raw": 2.6482,
                        "fmt": "2.65"
                    },
                    "fiscalQuarter": "3Q2025",
                    "calendarQuarter": "3Q2025",
                    "difference": "0.13",
                    "surprisePct": "4.98"
                }
            ],
            "currentQuarterEstimate": {
                "raw": 2.80649,
                "fmt": "2.81"
            },
            "currentQuarterEstimateDate": "4Q",
            "currentCalendarQuarter": "4Q2025",
            "currentQuarterEstimateYear": 2025,
            "currentFiscalQuarter": "4Q2025",
            "earningsDate": [
                {
                    "raw": 1768570200,
                    "fmt": "2026-01-16"
                }
            ],
            "isEarningsDateEstimate": false
        },
        "financialsChart": {
            "yearly": [
                {
                    "date": 2021,
                    "revenue": {
                        "raw": 12027000000,
                        "fmt": "12.03B",
                        "longFmt": "12,027,000,000"
                    },
                    "earnings": {
                        "raw": 2665000000,
                        "fmt": "2.67B",
                        "longFmt": "2,665,000,000"
                    }
                },
                {
                    "date": 2022,
                    "revenue": {
                        "raw": 12148000000,
                        "fmt": "12.15B",
                        "longFmt": "12,148,000,000"
                    },
                    "earnings": {
                        "raw": 2743000000,
                        "fmt": "2.74B",
                        "longFmt": "2,743,000,000"
                    }
                },
                {
                    "date": 2023,
                    "revenue": {
                        "raw": 11945000000,
                        "fmt": "11.95B",
                        "longFmt": "11,945,000,000"
                    },
                    "earnings": {
                        "raw": 2500000000,
                        "fmt": "2.5B",
                        "longFmt": "2,500,000,000"
                    }
                },
                {
                    "date": 2024,
                    "revenue": {
                        "raw": 13000000000,
                        "fmt": "13B",
                        "longFmt": "13,000,000,000"
                    },
                    "earnings": {
                        "raw": 2623000000,
                        "fmt": "2.62B",
                        "longFmt": "2,623,000,000"
                    }
                }
            ],
            "quarterly": [
                {
                    "date": "4Q2024",
                    "fiscalQuarter": "4Q2024",
                    "revenue": {
                        "raw": 3412000000,
                        "fmt": "3.41B",
                        "longFmt": "3,412,000,000"
                    },
                    "earnings": {
                        "raw": 769000000,
                        "fmt": "769M",
                        "longFmt": "769,000,000"
                    }
                },
                {
                    "date": "1Q2025",
                    "fiscalQuarter": "1Q2025",
                    "revenue": {
                        "raw": 3284000000,
                        "fmt": "3.28B",
                        "longFmt": "3,284,000,000"
                    },
                    "earnings": {
                        "raw": 597000000,
                        "fmt": "597M",
                        "longFmt": "597,000,000"
                    }
                },
                {
                    "date": "2Q2025",
                    "fiscalQuarter": "2Q2025",
                    "revenue": {
                        "raw": 3448000000,
                        "fmt": "3.45B",
                        "longFmt": "3,448,000,000"
                    },
                    "earnings": {
                        "raw": 733000000,
                        "fmt": "733M",
                        "longFmt": "733,000,000"
                    }
                },
                {
                    "date": "3Q2025",
                    "fiscalQuarter": "3Q2025",
                    "revenue": {
                        "raw": 3545000000,
                        "fmt": "3.54B",
                        "longFmt": "3,545,000,000"
                    },
                    "earnings": {
                        "raw": 802000000,
                        "fmt": "802M",
                        "longFmt": "802,000,000"
                    }
                }
            ]
        },
        "financialCurrency": "USD",
        "defaultMethodology": "nongaap"
    },
    "calendarEvents": {
        "maxAge": 1,
        "earnings": {
            "earningsDate": [
                {
                    "raw": 1768570200,
                    "fmt": "2026-01-16"
                }
            ],
            "earningsCallDate": [
                {
                    "raw": 1768579200,
                    "fmt": "2026-01-16"
                }
            ],
            "isEarningsDateEstimate": false,
            "earningsAverage": {
                "raw": 2.80649,
                "fmt": "2.81"
            },
            "earningsLow": {
                "raw": 2.71,
                "fmt": "2.71"
            },
            "earningsHigh": {
                "raw": 2.91,
                "fmt": "2.91"
            },
            "revenueAverage": {
                "raw": 3568238690,
                "fmt": "3.57B",
                "longFmt": "3,568,238,690"
            },
            "revenueLow": {
                "raw": 3531541860,
                "fmt": "3.53B",
                "longFmt": "3,531,541,860"
            },
            "revenueHigh": {
                "raw": 3607000000,
                "fmt": "3.61B",
                "longFmt": "3,607,000,000"
            }
        },
        "exDividendDate": {
            "raw": 1767312000,
            "fmt": "2026-01-02"
        },
        "dividendDate": {
            "raw": 1768176000,
            "fmt": "2026-01-12"
        }
    },
    "pageViews": {
        "shortTermTrend": "NEUTRAL",
        "midTermTrend": "UP",
        "longTermTrend": "UP",
        "maxAge": 1
    },
    "price": {
        "maxAge": 1,
        "preMarketChangePercent": {
            "raw": -7.555569e-05,
            "fmt": "-0.01%"
        },
        "preMarketChange": {
            "raw": -0.009994507,
            "fmt": "-0.01"
        },
        "preMarketTime": 1767016835,
        "preMarketPrice": {
            "raw": 132.27,
            "fmt": "132.27"
        },
        "preMarketSource": "DELAYED",
        "postMarketChangePercent": {
            "raw": 0.0031134,
            "fmt": "0.31%"
        },
        "postMarketChange": {
            "raw": 0.41000366,
            "fmt": "0.41"
        },
        "postMarketTime": 1767056134,
        "postMarketPrice": {
            "raw": 132.1,
            "fmt": "132.10"
        },
        "postMarketSource": "DELAYED",
        "regularMarketChangePercent": {
            "raw": -0.00446021,
            "fmt": "-0.45%"
        },
        "regularMarketChange": {
            "raw": -0.589996,
            "fmt": "-0.59"
        },
        "regularMarketTime": 1767042002,
        "priceHint": {
            "raw": 2,
            "fmt": "2",
            "longFmt": "2"
        },
        "regularMarketPrice": {
            "raw": 131.69,
            "fmt": "131.69"
        },
        "regularMarketDayHigh": {
            "raw": 132.95,
            "fmt": "132.95"
        },
        "regularMarketDayLow": {
            "raw": 130.62,
            "fmt": "130.62"
        },
        "regularMarketVolume": {
            "raw": 922960,
            "fmt": "922.96k",
            "longFmt": "922,960.00"
        },
        "averageDailyVolume10Day": {
            "raw": 2327180,
            "fmt": "2.33M",
            "longFmt": "2,327,180"
        },
        "averageDailyVolume3Month": {
            "raw": 2006393,
            "fmt": "2.01M",
            "longFmt": "2,006,393"
        },
        "regularMarketPreviousClose": {
            "raw": 132.28,
            "fmt": "132.28"
        },
        "regularMarketSource": "FREE_REALTIME",
        "regularMarketOpen": {
            "raw": 132.23,
            "fmt": "132.23"
        },
        "strikePrice": {},
        "openInterest": {},
        "exchange": "NYQ",
        "exchangeName": "NYSE",
        "exchangeDataDelayedBy": 0,
        "marketState": "POSTPOST",
        "quoteType": "EQUITY",
        "symbol": "STT",
        "underlyingSymbol": null,
        "shortName": "State Street Corporation",
        "longName": "State Street Corporation",
        "currency": "USD",
        "quoteSourceName": "Delayed Quote",
        "currencySymbol": "$",
        "fromCurrency": null,
        "toCurrency": null,
        "lastMarket": null,
        "volume24Hr": {},
        "volumeAllCurrencies": {},
        "circulatingSupply": {},
        "marketCap": {
            "raw": 37359837184,
            "fmt": "37.36B",
            "longFmt": "37,359,837,184.00"
        }
    },
    "corporateActions": {
        "corporateActions": [
            {
                "header": "Dividend",
                "message": "STT announced a cash dividend of 0.84 with an ex-date of Jan. 2, 2026",
                "meta": {
                    "eventType": "DIVIDEND",
                    "dateEpochMs": 1767330000000,
                    "amount": "0.84"
                }
            }
        ],
        "maxAge": 1
    },
    "financialData": {
        "maxAge": 86400,
        "currentPrice": {
            "raw": 131.69,
            "fmt": "131.69"
        },
        "targetHighPrice": {
            "raw": 168.0,
            "fmt": "168.00"
        },
        "targetLowPrice": {
            "raw": 102.0,
            "fmt": "102.00"
        },
        "targetMeanPrice": {
            "raw": 130.66667,
            "fmt": "130.67"
        },
        "targetMedianPrice": {
            "raw": 131.0,
            "fmt": "131.00"
        },
        "recommendationMean": {
            "raw": 1.88235,
            "fmt": "1.88"
        },
        "recommendationKey": "buy",
        "numberOfAnalystOpinions": {
            "raw": 15,
            "fmt": "15",
            "longFmt": "15"
        },
        "totalCash": {
            "raw": 139566006272,
            "fmt": "139.57B",
            "longFmt": "139,566,006,272"
        },
        "totalCashPerShare": {
            "raw": 499.677,
            "fmt": "499.68"
        },
        "ebitda": {},
        "totalDebt": {
            "raw": 54206001152,
            "fmt": "54.21B",
            "longFmt": "54,206,001,152"
        },
        "quickRatio": {},
        "currentRatio": {},
        "totalRevenue": {
            "raw": 13626000384,
            "fmt": "13.63B",
            "longFmt": "13,626,000,384"
        },
        "debtToEquity": {},
        "revenuePerShare": {
            "raw": 47.4,
            "fmt": "47.40"
        },
        "returnOnAssets": {
            "raw": 0.0084,
            "fmt": "0.84%"
        },
        "returnOnEquity": {
            "raw": 0.111499995,
            "fmt": "11.15%"
        },
        "grossProfits": {
            "raw": 13626000384,
            "fmt": "13.63B",
            "longFmt": "13,626,000,384"
        },
        "freeCashflow": {},
        "operatingCashflow": {
            "raw": -5574000128,
            "fmt": "-5.57B",
            "longFmt": "-5,574,000,128"
        },
        "earningsGrowth": {
            "raw": 0.23,
            "fmt": "23.00%"
        },
        "revenueGrowth": {
            "raw": 0.094,
            "fmt": "9.40%"
        },
        "grossMargins": {
            "raw": 0.0,
            "fmt": "0.00%"
        },
        "ebitdaMargins": {
            "raw": 0.0,
            "fmt": "0.00%"
        },
        "operatingMargins": {
            "raw": 0.32749,
            "fmt": "32.75%"
        },
        "profitMargins": {
            "raw": 0.21877001,
            "fmt": "21.88%"
        },
        "financialCurrency": "USD"
    }
}